{
  "last_update": "2025-12-20 03:18",
  "market": [
    {
      "name": "میلگرد ۱۴ (ذوب)",
      "price": "۲۶,۲۰۰"
    },
    {
      "name": "تیرآهن ۱۶",
      "price": "۴,۸۰۰,۰۰۰"
    },
    {
      "name": "سیمان پاکتی",
      "price": "۷۹,۰۰۰"
    },
    {
      "name": "دلار آزاد",
      "price": "۶۰,۹۰۰"
    }
  ],
  "news": [
    {
      "title": "انجام ۲ هزار کیلومتر برف‌روبی در محورهای کرمان/ باز بودن محورهای شریانی و ۲۵ گردنه برف‌گیر استان",
      "link": "http://news.mrud.ir/news/212035/انجام-۲-هزار-کیلومتر-برف-روبی-در-محورهای-کرمان-باز-بودن-محورهای",
      "source": "وزارت راه و شهرسازی"
    },
    {
      "title": "جلوگیری از انسداد محورهای استان البرز با تلاش شبانه‌روزی راهداران",
      "link": "http://news.mrud.ir/news/212034/جلوگیری-از-انسداد-محورهای-استان-البرز-با-تلاش-شبانه-روزی-راهداران",
      "source": "وزارت راه و شهرسازی"
    },
    {
      "title": "آغاز عملیات گسترده راهداری زمستانی با ۹ هزار دستگاه و ۱۲ هزار نیروی انسانی در کشور",
      "link": "http://news.mrud.ir/news/212033/آغاز-عملیات-گسترده-راهداری-زمستانی-با-۹-هزار-دستگاه-و-۱۲-هزار",
      "source": "وزارت راه و شهرسازی"
    },
    {
      "title": "ویدئو| نشست خبری مدیرکل راهداری و حمل و نقل جاده ای آذربایجان شرقی با اصحاب رسانه",
      "link": "http://news.mrud.ir/news/212023/ویدئو-نشست-خبری-مدیرکل-راهداری-و-حمل-و-نقل-جاده-ای-آذربایجان",
      "source": "وزارت راه و شهرسازی"
    },
    {
      "title": "از یک الزام مقرراتی تا موتور محرک توسعه پایدار در ساختمان",
      "link": "https://www.ghatreh.com/news/nn14040903595606685696/%D8%A7%D8%B2-%DB%8C%DA%A9-%D8%A7%D9%84%D8%B2%D8%A7%D9%85-%D9%85%D9%82%D8%B1%D8%B1%D8%A7%D8%AA%DB%8C-%D8%AA%D8%A7-%D9%85%D9%88%D8%AA%D9%88%D8%B1-%D9%85%D8%AD%D8%B1%DA%A9-%D8%AA%D9%88%D8%B3%D8%B9%D9%87-%D9%BE%D8%A7%DB%8C%D8%AF%D8%A7%D8%B1-%D8%AF%D8%B1",
      "source": "قطره (ساختمان)"
    },
    {
      "title": "پایان کار ساختمان ها بدون شناسنامه انرژی صادر نمی شود",
      "link": "https://www.ghatreh.com/news/nn14040932122873972736/%D9%BE%D8%A7%DB%8C%D8%A7%D9%86-%DA%A9%D8%A7%D8%B1-%D8%B3%D8%A7%D8%AE%D8%AA%D9%85%D8%A7%D9%86-%D9%87%D8%A7-%D8%A8%D8%AF%D9%88%D9%86-%D8%B4%D9%86%D8%A7%D8%B3%D9%86%D8%A7%D9%85%D9%87-%D8%A7%D9%86%D8%B1%DA%98%DB%8C-%D8%B5%D8%A7%D8%AF%D8%B1-%D9%86%D9%85%DB%8C-%D8%B4%D9%88%D8%AF",
      "source": "قطره (ساختمان)"
    },
    {
      "title": "برگزاری همایش  نقشه راه مشترک؛ ساخت وساز و حمل ونقل پایدار  در قزوین",
      "link": "https://www.ghatreh.com/news/nn14040929172817416192/%D8%A8%D8%B1%DA%AF%D8%B2%D8%A7%D8%B1%DB%8C-%D9%87%D9%85%D8%A7%DB%8C%D8%B4-%C2%AB%D9%86%D9%82%D8%B4%D9%87-%D8%B1%D8%A7%D9%87-%D9%85%D8%B4%D8%AA%D8%B1%DA%A9%D8%9B-%D8%B3%D8%A7%D8%AE%D8%AA-%D9%88%D8%B3%D8%A7%D8%B2-%D9%88-%D8%AD%D9%85%D9%84-%D9%88%D9%86%D9%82%D9%84",
      "source": "قطره (ساختمان)"
    },
    {
      "title": "رییس  نظام مهندسی ساختمان البرز: همکاری شهرداری ها بهتر شده است",
      "link": "https://www.ghatreh.com/news/nn14040948198944698368/%D8%B1%DB%8C%DB%8C%D8%B3%C2%A0-%D9%86%D8%B8%D8%A7%D9%85-%D9%85%D9%87%D9%86%D8%AF%D8%B3%DB%8C-%D8%B3%D8%A7%D8%AE%D8%AA%D9%85%D8%A7%D9%86-%D8%A7%D9%84%D8%A8%D8%B1%D8%B2%3A-%D9%87%D9%85%DA%A9%D8%A7%D8%B1%DB%8C-%D8%B4%D9%87%D8%B1%D8%AF%D8%A7%D8%B1%DB%8C-%D9%87%D8%A7-%D8%A8%D9%87%D8%AA%D8%B1-%D8%B4%D8%AF%D9%87",
      "source": "قطره (ساختمان)"
    },
    {
      "title": "تقویت نظارت درون‌سازمانی و شفافیت، راهبرد اصلی شورای دهم است",
      "link": "https://irceo.ir/index.php/archive/news/item/36181",
      "source": "نظام مهندسی کشور"
    },
    {
      "title": "تأکید رئیس سازمان نظام مهندسی ساختمان بر تقویت شوراهای انتظامی، تسریع رسیدگی‌ها و نقش سامانه جامع",
      "link": "https://irceo.ir/index.php/archive/news/item/36180",
      "source": "نظام مهندسی کشور"
    },
    {
      "title": "برگزاری جلسه کارگروه انرژی ساختمان دبیرخانه مجمع تشخیص مصلحت نظام با حضور دستگاه‌های اجرایی",
      "link": "https://irceo.ir/index.php/archive/news/item/36179",
      "source": "نظام مهندسی کشور"
    },
    {
      "title": "گزارش تصویری نخستین جلسه رؤسا، خزانه‌داران و بازرسان سازمان نظام مهندسی ساختمان",
      "link": "https://irceo.ir/index.php/archive/news/item/36178",
      "source": "نظام مهندسی کشور"
    }
  ],
  "regulations": {
    "9": "https://inbr.ir",
    "10": "https://inbr.ir"
  }
}